yamelish/__init__.py
yamelish/__main__.py
yamelish/cli.py
yamelish/handlers.py
yamelish-1.0.0.dist-info/COPYING
yamelish-1.0.0.dist-info/METADATA
yamelish-1.0.0.dist-info/WHEEL
yamelish-1.0.0.dist-info/entry_points.txt
yamelish-1.0.0.dist-info/top_level.txt
yamelish-1.0.0.dist-info/RECORD
