Metadata-Version: 2.1
Name: yamelish
Version: 1.0.0
Summary: YAML-ish, non parsable format, suitable to diff JSON data
Home-page: https://github.com/xavierog/yamelish
Author: Xavier G.
Author-email: xavier.yamelish@kindwolf.org
License: WTFPL
Keywords: cli,json,yaml,diff
Platform: UNKNOWN
Classifier: Operating System :: POSIX :: Linux
Classifier: Programming Language :: Python :: 3 :: Only
Classifier: Topic :: Text Processing
License-File: COPYING
